apiclient-stubs/__init__.pyi
apiclient-stubs/channel.pyi
apiclient-stubs/discovery.pyi
apiclient-stubs/errors.pyi
apiclient-stubs/http.pyi
apiclient-stubs/mimeparse.pyi
apiclient-stubs/model.pyi
apiclient-stubs/sample_tools.pyi
apiclient-stubs/schema.pyi
apiclient-stubs/version.pyi
googleapiclient-stubs/__init__.pyi
googleapiclient-stubs/_apis/__init__.pyi
googleapiclient-stubs/_apis/abusiveexperiencereport/__init__.pyi
googleapiclient-stubs/_apis/abusiveexperiencereport/v1/__init__.pyi
googleapiclient-stubs/_apis/abusiveexperiencereport/v1/resources.pyi
googleapiclient-stubs/_apis/abusiveexperiencereport/v1/schemas.pyi
googleapiclient-stubs/_apis/acceleratedmobilepageurl/__init__.pyi
googleapiclient-stubs/_apis/acceleratedmobilepageurl/v1/__init__.pyi
googleapiclient-stubs/_apis/acceleratedmobilepageurl/v1/resources.pyi
googleapiclient-stubs/_apis/acceleratedmobilepageurl/v1/schemas.pyi
googleapiclient-stubs/_apis/accessapproval/__init__.pyi
googleapiclient-stubs/_apis/accessapproval/v1/__init__.pyi
googleapiclient-stubs/_apis/accessapproval/v1/resources.pyi
googleapiclient-stubs/_apis/accessapproval/v1/schemas.pyi
googleapiclient-stubs/_apis/accesscontextmanager/__init__.pyi
googleapiclient-stubs/_apis/accesscontextmanager/v1/__init__.pyi
googleapiclient-stubs/_apis/accesscontextmanager/v1/resources.pyi
googleapiclient-stubs/_apis/accesscontextmanager/v1/schemas.pyi
googleapiclient-stubs/_apis/accesscontextmanager/v1beta/__init__.pyi
googleapiclient-stubs/_apis/accesscontextmanager/v1beta/resources.pyi
googleapiclient-stubs/_apis/accesscontextmanager/v1beta/schemas.pyi
googleapiclient-stubs/_apis/acmedns/__init__.pyi
googleapiclient-stubs/_apis/acmedns/v1/__init__.pyi
googleapiclient-stubs/_apis/acmedns/v1/resources.pyi
googleapiclient-stubs/_apis/acmedns/v1/schemas.pyi
googleapiclient-stubs/_apis/addressvalidation/__init__.pyi
googleapiclient-stubs/_apis/addressvalidation/v1/__init__.pyi
googleapiclient-stubs/_apis/addressvalidation/v1/resources.pyi
google_api_python_client_stubs-1.26.0.dist-info/LICENSE
google_api_python_client_stubs-1.26.0.dist-info/METADATA
google_api_python_client_stubs-1.26.0.dist-info/WHEEL
google_api_python_client_stubs-1.26.0.dist-info/RECORD
