Metadata-Version: 2.1
Name: google-api-python-client-stubs
Version: 1.26.0
Summary: Type stubs for google-api-python-client
Home-page: https://github.com/henribru/google-api-python-client-stubs
License: Apache-2.0
Author: Henrik Bruådal
Author-email: henrik.bruasdal@gmail.com
Requires-Python: >=3.7,<4.0
Classifier: License :: OSI Approved :: Apache Software License
Classifier: Programming Language :: Python :: 3
Classifier: Programming Language :: Python :: 3.7
Classifier: Programming Language :: Python :: 3.8
Classifier: Programming Language :: Python :: 3.9
Classifier: Programming Language :: Python :: 3.10
Classifier: Programming Language :: Python :: 3.11
Classifier: Programming Language :: Python :: 3.12
Classifier: Typing :: Stubs Only
Requires-Dist: google-api-python-client (>=2.130.0)
Requires-Dist: types-httplib2 (>=0.22.0.2)
Requires-Dist: typing-extensions (>=3.10.0)
Project-URL: Repository, https://github.com/henribru/google-api-python-client-stubs
